{
    "sourceFile": "back-end/src/views/email.hbs",
    "activeCommit": 0,
    "commits": [
        {
            "activePatchIndex": 0,
            "patches": [
                {
                    "date": 1655991761728,
                    "content": "Index: \n===================================================================\n--- \n+++ \n"
                }
            ],
            "date": 1655991761728,
            "name": "Commit-0",
            "content": "<html lang=\"en\" xmlns=\"http://www.w3.org/1999/xhtml\" xmlns:v=\"urn:schemas-microsoft-com:vml\"\r\n  xmlns:o=\"urn:schemas-microsoft-com:office:office\">\r\n\r\n<head>\r\n  <meta charset=\"utf-8\" />\r\n  <meta name=\"viewport\" content=\"width=device-width\" />\r\n  <meta http-equiv=\"X-UA-Compatible\" content=\"IE=edge\" />\r\n  <meta name=\"x-apple-disable-message-reformatting\" />\r\n  <title></title>\r\n\r\n  <link href=\"https://fonts.googleapis.com/css?family=Poppins:200,300,400,500,600,700\" rel=\"stylesheet\" />\r\n\r\n  <style>\r\n    html,\r\n    body {\r\n      margin: 0 auto !important;\r\n      padding: 0 !important;\r\n      height: 100% !important;\r\n      width: 100% !important;\r\n      background: #f1f1f1;\r\n    }\r\n\r\n    * {\r\n      -ms-text-size-adjust: 100%;\r\n      -webkit-text-size-adjust: 100%;\r\n    }\r\n\r\n    div[style*=\"margin: 16px 0\"] {\r\n      margin: 0 !important;\r\n    }\r\n\r\n    table,\r\n    td {\r\n      mso-table-lspace: 0pt !important;\r\n      mso-table-rspace: 0pt !important;\r\n    }\r\n\r\n    table {\r\n      border-spacing: 0 !important;\r\n      border-collapse: collapse !important;\r\n      table-layout: fixed !important;\r\n      margin: 0 auto !important;\r\n    }\r\n\r\n    img {\r\n      -ms-interpolation-mode: bicubic;\r\n    }\r\n\r\n    a {\r\n      text-decoration: none;\r\n    }\r\n\r\n\r\n    *[x-apple-data-detectors],\r\n    .unstyle-auto-detected-links *,\r\n    .aBn {\r\n      border-bottom: 0 !important;\r\n      cursor: default !important;\r\n      color: inherit !important;\r\n      text-decoration: none !important;\r\n      font-size: inherit !important;\r\n      font-family: inherit !important;\r\n      font-weight: inherit !important;\r\n      line-height: inherit !important;\r\n    }\r\n\r\n    .a6S {\r\n      display: none !important;\r\n      opacity: 0.01 !important;\r\n    }\r\n\r\n    .im {\r\n      color: inherit !important;\r\n    }\r\n\r\n    img.g-img+div {\r\n      display: none !important;\r\n    }\r\n\r\n    @media only screen and (min-device-width: 320px) and (max-device-width: 374px) {\r\n      u~div .email-container {\r\n        min-width: 320px !important;\r\n      }\r\n    }\r\n\r\n    @media only screen and (min-device-width: 375px) and (max-device-width: 413px) {\r\n      u~div .email-container {\r\n        min-width: 375px !important;\r\n      }\r\n    }\r\n\r\n    @media only screen and (min-device-width: 414px) {\r\n      u~div .email-container {\r\n        min-width: 414px !important;\r\n      }\r\n    }\r\n  </style>\r\n  <style>\r\n    .primary {\r\n      background: #1565c0;\r\n    }\r\n\r\n    .bg_white {\r\n      background: #ffffff;\r\n    }\r\n\r\n    .bg_light {\r\n      background: #f7fafa;\r\n    }\r\n\r\n    .bg_black {\r\n      background: #000000;\r\n    }\r\n\r\n    .bg_dark {\r\n      background: rgba(0, 0, 0, .8);\r\n    }\r\n\r\n    .email-section {\r\n      padding:\r\n        2.5em;\r\n    }\r\n\r\n    .btn {\r\n      padding: 10px 15px;\r\n      display: inline-block;\r\n    }\r\n\r\n    .btn.btn-primary {\r\n      border-radius: 5px;\r\n      background: #17bebb;\r\n      color:\r\n        #ffffff;\r\n    }\r\n\r\n    .btn.btn-white {\r\n      border-radius: 5px;\r\n      background: #ffffff;\r\n      color: #000000;\r\n    }\r\n\r\n    .btn.btn-white-outline {\r\n      border-radius: 5px;\r\n      background:\r\n        transparent;\r\nborder: 1px solid #fff;\r\n      color: #fff;\r\n    }\r\n\r\n    .btn.btn-black-outline {\r\n      border-radius: 0px;\r\n      background: transparent;\r\n      border: 2px solid #000;\r\n      color: #000;\r\n      font-weight: 700;\r\n    }\r\n\r\n    .btn-custom {\r\n      color: rgba(0, 0, 0, .3);\r\n      text-decoration: underline;\r\n    }\r\n\r\n    h1,\r\n    h2,\r\n    h3,\r\n    h4,\r\n    h5,\r\n    h6 {\r\n      font-family:\r\n        'Poppins', sans-serif;\r\n      color: #000000;\r\n      margin-top: 0;\r\n      font-weight: 400;\r\n      margin-bottom: 5px;\r\n    }\r\n\r\n    body {\r\n      font-family: 'Poppins', sans-serif;\r\n      font-weight: 400;\r\n      font-size:\r\n        15px;\r\n      line-height: 1.8;\r\n      color: rgba(0, 0, 0, .4);\r\n    }\r\n\r\n    a {\r\n      color: #17bebb;\r\n    }\r\n\r\n    table {}\r\n\r\n    .logo h1 {\r\n      margin: 0;\r\n    }\r\n\r\n    .logo h1 a {\r\n      color: #3498db;\r\n      font-size:\r\n        24px;\r\n      font-weight: 700;\r\n      font-family: 'Poppins', sans-serif;\r\n    }\r\n\r\n    .hero {\r\n      position: relative;\r\n      z-index: 0;\r\n    }\r\n\r\n    .hero .text {\r\n      color: rgba(0, 0, 0, .3);\r\n    }\r\n\r\n    .hero .text h2 {\r\n      color: #000;\r\n      font-size: 34px;\r\n      margin-bottom: 0;\r\n      font-weight: 200;\r\n      line-height: 1.4;\r\n    }\r\n\r\n    .hero .text h3 {\r\n      font-size: 24px;\r\n      font-weight: 300;\r\n    }\r\n\r\n    .hero .text h2 span {\r\n      font-weight: 600;\r\n      color: #000;\r\n    }\r\n\r\n    .text-author {\r\n      padding: 24px;\r\n    }\r\n\r\n    .text-author img {\r\n      border-radius: 50%;\r\n      padding-bottom: 20px;\r\n    }\r\n\r\n    .text-author h3 {\r\n      margin-bottom: 0;\r\n    }\r\n\r\n    ul.social {\r\n      padding: 0;\r\n    }\r\n\r\n    ul.social li {\r\n      display: inline-block;\r\n      margin-right: 10px;\r\n    }\r\n\r\n    .footer {\r\n      border-top: 1px solid rgba(0, 0, 0, .05);\r\n      color: rgba(0, 0, 0,\r\n          .5);\r\n    }\r\n\r\n    .footer .heading {\r\n      color: #000;\r\n      font-size: 20px;\r\n    }\r\n\r\n    .footer ul {\r\n      margin: 0;\r\n      padding: 0;\r\n    }\r\n\r\n    .footer ul li {\r\n      list-style: none;\r\n      margin-bottom:\r\n        10px;\r\n    }\r\n\r\n    .footer ul li a {\r\n      color: rgba(0, 0, 0, 1);\r\n    }\r\n\r\n    @media screen and (max-width: 500px) {}\r\n  </style>\r\n</head>\r\n\r\n<body width=\"100%\" style=\"margin: 0; padding: 0 !important; mso-line-height-rule: exactly; background-color: #f1f1f1;\">\r\n  <center style=\"width: 100%; background-color: #f1f2f2;padding:24px;\">\r\n    <div\r\n      style=\"display: none; font-size: 1px;max-height: 0px; max-width: 0px; opacity: 0; overflow: hidden; mso-hide: all; font-family: sans-serif;\">\r\n      &zwnj;&nbsp;&zwnj;&nbsp;&zwnj;&nbsp;&zwnj;&nbsp;&zwnj;&nbsp;&zwnj;&nbsp;&zwnj;&nbsp;&zwnj;&nbsp;&zwnj;&nbsp;&zwnj;&nbsp;&zwnj;&nbsp;&zwnj;&nbsp;&zwnj;&nbsp;&zwnj;&nbsp;&zwnj;&nbsp;&zwnj;&nbsp;&zwnj;&nbsp;&zwnj;&nbsp;\r\n    </div>\r\n    <div style=\"max-width: 510px; margin: 0 auto;\" class=\"email-container\">\r\n      <table color=\"white\" align=\"center\" role=\"presentation\" cellspacing=\"0\" cellpadding=\"0\" border=\"0\" width=\"100%\"\r\n        style=\"background-color: white;border-radius: 12px;\">\r\n        <tr>\r\n<td valign=\"top\" class=\"primary\" style=\"padding: 10px 16px; border-radius: 12px;\">\r\n            <table role=\"presentation\" border=\"0\" cellpadding=\"0\" cellspacing=\"0\" width=\"100%\">\r\n              <tr style=\"display: flow-root;\">\r\n                <td class=\"logo\" style=\"text-align: left;\">\r\n                  <img src=\"https://sv.dntu.edu.vn/images/dntu-logo.png\" alt=\"\" style=\"width:53px;\" />\r\n                </td>\r\n                <td class=\"text\"\r\n                  style=\"text-align: left; font-size: 28px; font-weight: bold; color: white;padding-left:8px\">\r\n                  <h3 style=\"color:white\">Hôm nay trời đẹp quá</h3>\r\n                </td>\r\n              </tr>\r\n            </table>\r\n          </td>\r\n        </tr>\r\n        <tr>\r\n          <td valign=\"middle\" class=\"hero bg_white\" style=\"padding: 16px;\">\r\n            <table role=\"presentation\" border=\"0\" cellpadding=\"0\" cellspacing=\"0\" width=\"100%\">\r\n              <tr>\r\n                <td style=\"padding: 16px 24px; text-align: center;\">\r\n                  <div class=\"text\">\r\n                    <h3>Đại Học Công Nghệ Đồng Nai</h3>\r\n                  </div>\r\n                </td>\r\n              </tr>\r\n              <tr>\r\n                <td style=\"text-align: center;\">\r\n                  <div class=\"text-author\">\r\n                    <h3 class=\"name\">Xin chào {{username}}</h3>\r\n                    <h4 class=\"name\" style=\"text-align: left;\">Bạn được duyệt vào đợt thực tập\r\n                      {{title}}. Vui lòng đăng nhập hệ thống để đăng ký đợt thực tập.</h4>\r\n                    <h4 style=\"text-align: left;\"> Tài Khoản: {{email}}</h4>\r\n                    <h4 style=\"text-align: left;\"> Mật khẩu: {{password}}</h4>\r\n                    <p><a href=\"#\" class=\"btn btn-primary\">Đăng Nhập</a></p>\r\n                  </div>\r\n                </td>\r\n              </tr>\r\n            </table>\r\n          </td>\r\n        </tr>\r\n        <tr>\r\n          <td valign=\"bottom\" class=\"primary\" style=\"border-radius: 12px;\">\r\n            <table role=\"presentation\" border=\"0\" cellpadding=\"0\" cellspacing=\"0\" width=\"100%\">\r\n              <tr>\r\n                <td style=\"text-align: left; padding: 12px 24px; color:white;\">\r\n                  <p style=\"margin:0px;\">Về chúng tôi</p>\r\n                  <p style=\"margin:0px;\">Team IT là những người đẹp trai nhất hành tình này</p>\r\n                  <p style=\"margin:0px;\">Địa chỉ: KP2, P.Tân Biên, Biên Hòa, Đồng Nai</p>\r\n                </td>\r\n              </tr>\r\n            </table>\r\n          </td>\r\n        </tr>\r\n      </table>\r\n    </div>\r\n  </center>\r\n</body>\r\n\r\n</html>"
        }
    ]
}